pingze_classifier/__init__.py
pingze_classifier/classifier.py
pingze_classifier/scraper.py
pingze_classifier/data/organized_ping_ze_rhyme_dict.json
tests/__init__.py
tests/test_classifier.py
pingze_classifier-0.11.dist-info/LICENSE
pingze_classifier-0.11.dist-info/METADATA
pingze_classifier-0.11.dist-info/WHEEL
pingze_classifier-0.11.dist-info/entry_points.txt
pingze_classifier-0.11.dist-info/top_level.txt
pingze_classifier-0.11.dist-info/RECORD
