Metadata-Version: 2.1
Name: pingze_classifier
Version: 0.11
Summary: A Python package for classifying Chinese characters based on the Pingshui rhyme scheme
Home-page: https://github.com/rbnyng/pingze_classifier
Author: rbnyng
Author-email: 
Classifier: Programming Language :: Python :: 3
Classifier: License :: OSI Approved :: MIT License
Classifier: Operating System :: OS Independent
Requires-Python: >=3.6
License-File: LICENSE
Requires-Dist: beautifulsoup4
Requires-Dist: requests
Provides-Extra: dev
Requires-Dist: pytest; extra == "dev"
Requires-Dist: coverage; extra == "dev"
